spacecoords/__init__.py
spacecoords/celestial.py
spacecoords/cli.py
spacecoords/constants.py
spacecoords/download.py
spacecoords/frames.py
spacecoords/linalg.py
spacecoords/projection.py
spacecoords/py.typed
spacecoords/spherical.py
spacecoords/spice.py
spacecoords/spk_basic.py
spacecoords/types.py
spacecoords/version.py
spacecoords-0.1.5.dist-info/licenses/LICENSE
spacecoords-0.1.5.dist-info/METADATA
spacecoords-0.1.5.dist-info/WHEEL
spacecoords-0.1.5.dist-info/entry_points.txt
spacecoords-0.1.5.dist-info/top_level.txt
spacecoords-0.1.5.dist-info/RECORD
