Metadata-Version: 2.4
Name: spacecoords
Version: 0.1.5
Summary: A collection of coordinate transforms for convenient use
Author-email: Daniel Kastinen <daniel.kastinen@irf.se>
Maintainer-email: Daniel Kastinen <daniel.kastinen@irf.se>
License: MIT License
Project-URL: Documentation, https://danielk.developer.irf.se/spacecoords/
Project-URL: Repository, https://github.com/danielk333/spacecoords
Classifier: Intended Audience :: Science/Research
Classifier: Programming Language :: Python :: 3
Classifier: Topic :: Scientific/Engineering :: Physics
Classifier: Operating System :: OS Independent
Classifier: License :: OSI Approved :: MIT License
Requires-Python: >=3.10
License-File: LICENSE
Requires-Dist: numpy>=2
Provides-Extra: all
Requires-Dist: astropy>=6; extra == "all"
Requires-Dist: spiceypy>=8.0.0; extra == "all"
Requires-Dist: jplephem>=2.23; extra == "all"
Requires-Dist: requests>=2.20; extra == "all"
Provides-Extra: develop
Requires-Dist: pytest; extra == "develop"
Requires-Dist: pytest-cov; extra == "develop"
Requires-Dist: flake8; extra == "develop"
Requires-Dist: wheel; extra == "develop"
Requires-Dist: build; extra == "develop"
Requires-Dist: twine; extra == "develop"
Requires-Dist: auditwheel; extra == "develop"
Requires-Dist: numpydoc; extra == "develop"
Requires-Dist: black; extra == "develop"
Requires-Dist: matplotlib; extra == "develop"
Requires-Dist: ipykernel; extra == "develop"
Requires-Dist: mkdocs-material; extra == "develop"
Requires-Dist: mkdocstrings[python]; extra == "develop"
Requires-Dist: mkdocs-jupyter; extra == "develop"
Requires-Dist: mkdocs-gen-files; extra == "develop"
Requires-Dist: mkdocs-literate-nav; extra == "develop"
Requires-Dist: mkdocs-section-index; extra == "develop"
Provides-Extra: tests
Requires-Dist: pytest; extra == "tests"
Requires-Dist: pytest-cov; extra == "tests"
Dynamic: license-file
